{
    "id": 362,
    "name": "Ice Radium Diablo V",
    "author": "12s",
    "creators": ["12s","sk80"],
    "verifier": "12s",
    "verification": "https://youtu.be/0AMQzrH13CQ",
    "percentToQualify": 100,
    "password": "Copyable",
    "records": [
        {
			"user": "doom",
			"link": "https://youtu.be/nonexistant",
			"percent": 100,
			"hz": 999
		},
        {
			"user": "sk80",
			"link": "https://youtu.be/nonexistant",
			"percent": 100,
			"hz": 240
		},
        {
			"user": "sk80",
			"link": "https://youtu.be/yz_lw2VCrr0",
			"percent": 100,
			"hz": 999
		}
    ]
}
